{"nodes": [{"id": "users_ajeet_projects_lbm_2d_src_orifice_plate_cpp", "label": "orifice_plate.cpp", "file_type": "code", "source_file": "src/orifice_plate.cpp", "source_location": "L1"}, {"id": "src_orifice_plate_orificeparams", "label": "OrificeParams", "file_type": "code", "source_file": "src/orifice_plate.cpp", "source_location": "L37"}, {"id": "src_orifice_plate_orificeparams_tau", "label": "tau", "file_type": "code", "source_file": "src/orifice_plate.cpp", "source_location": "L38"}, {"id": "src_orifice_plate_orificeparams_u_inflow", "label": "u_inflow", "file_type": "code", "source_file": "src/orifice_plate.cpp", "source_location": "L39"}, {"id": "src_orifice_plate_orificeparams_num_steps", "label": "num_steps", "file_type": "code", "source_file": "src/orifice_plate.cpp", "source_location": "L40"}, {"id": "src_orifice_plate_orificeparams_save_interval", "label": "save_interval", "file_type": "code", "source_file": "src/orifice_plate.cpp", "source_location": "L41"}, {"id": "src_orifice_plate_orificeparams_length_scale", "label": "length_scale", "file_type": "code", "source_file": "src/orifice_plate.cpp", "source_location": "L42"}, {"id": "string", "label": "string", "file_type": "code", "source_file": "src/orifice_plate.cpp", "source_location": "L43"}, {"id": "src_orifice_plate_orificeparams_config", "label": "config", "file_type": "code", "source_file": "src/orifice_plate.cpp", "source_location": "L43"}, {"id": "src_orifice_plate_orificeparams_hole_width", "label": "hole_width", "file_type": "code", "source_file": "src/orifice_plate.cpp", "source_location": "L44"}, {"id": "src_orifice_plate_orificeparams_plate_thickness", "label": "plate_thickness", "file_type": "code", "source_file": "src/orifice_plate.cpp", "source_location": "L45"}, {"id": "vector", "label": "vector", "file_type": "code", "source_file": "src/orifice_plate.cpp", "source_location": "L46"}, {"id": "src_orifice_plate_orificeparams_plate_cx", "label": "plate_cx", "file_type": "code", "source_file": "src/orifice_plate.cpp", "source_location": "L46"}, {"id": "src_orifice_plate_orificeparams_holes_cy", "label": "holes_cy", "file_type": "code", "source_file": "src/orifice_plate.cpp", "source_location": "L47"}, {"id": "src_orifice_plate_compute_params", "label": "compute_params()", "file_type": "code", "source_file": "src/orifice_plate.cpp", "source_location": "L50"}, {"id": "src_orifice_plate_place_orifice_plates", "label": "place_orifice_plates()", "file_type": "code", "source_file": "src/orifice_plate.cpp", "source_location": "L95"}, {"id": "lbmcapabilities", "label": "LBMCapabilities", "file_type": "code", "source_file": "src/orifice_plate.cpp", "source_location": "L95"}, {"id": "src_orifice_plate_main", "label": "main()", "file_type": "code", "source_file": "src/orifice_plate.cpp", "source_location": "L117"}], "edges": [{"source": "users_ajeet_projects_lbm_2d_src_orifice_plate_cpp", "target": "users_ajeet_projects_lbm_2d_src_lbm_hpp", "relation": "imports", "context": "import", "confidence": "EXTRACTED", "source_file": "src/orifice_plate.cpp", "source_location": "L1", "weight": 1.0}, {"source": "users_ajeet_projects_lbm_2d_src_orifice_plate_cpp", "target": "iostream", "relation": "imports", "context": "import", "confidence": "EXTRACTED", "source_file": "src/orifice_plate.cpp", "source_location": "L2", "weight": 1.0}, {"source": "users_ajeet_projects_lbm_2d_src_orifice_plate_cpp", "target": "iomanip", "relation": "imports", "context": "import", "confidence": "EXTRACTED", "source_file": "src/orifice_plate.cpp", "source_location": "L3", "weight": 1.0}, {"source": "users_ajeet_projects_lbm_2d_src_orifice_plate_cpp", "target": "cmath", "relation": "imports", "context": "import", "confidence": "EXTRACTED", "source_file": "src/orifice_plate.cpp", "source_location": "L4", "weight": 1.0}, {"source": "users_ajeet_projects_lbm_2d_src_orifice_plate_cpp", "target": "string", "relation": "imports", "context": "import", "confidence": "EXTRACTED", "source_file": "src/orifice_plate.cpp", "source_location": "L5", "weight": 1.0}, {"source": "users_ajeet_projects_lbm_2d_src_orifice_plate_cpp", "target": "filesystem", "relation": "imports", "context": "import", "confidence": "EXTRACTED", "source_file": "src/orifice_plate.cpp", "source_location": "L6", "weight": 1.0}, {"source": "users_ajeet_projects_lbm_2d_src_orifice_plate_cpp", "target": "vector", "relation": "imports", "context": "import", "confidence": "EXTRACTED", "source_file": "src/orifice_plate.cpp", "source_location": "L7", "weight": 1.0}, {"source": "users_ajeet_projects_lbm_2d_src_orifice_plate_cpp", "target": "src_orifice_plate_orificeparams", "relation": "contains", "confidence": "EXTRACTED", "source_file": "src/orifice_plate.cpp", "source_location": "L37", "weight": 1.0}, {"source": "src_orifice_plate_orificeparams", "target": "src_orifice_plate_orificeparams_tau", "relation": "defines", "confidence": "EXTRACTED", "source_file": "src/orifice_plate.cpp", "source_location": "L38", "weight": 1.0, "context": "field"}, {"source": "src_orifice_plate_orificeparams", "target": "src_orifice_plate_orificeparams_u_inflow", "relation": "defines", "confidence": "EXTRACTED", "source_file": "src/orifice_plate.cpp", "source_location": "L39", "weight": 1.0, "context": "field"}, {"source": "src_orifice_plate_orificeparams", "target": "src_orifice_plate_orificeparams_num_steps", "relation": "defines", "confidence": "EXTRACTED", "source_file": "src/orifice_plate.cpp", "source_location": "L40", "weight": 1.0, "context": "field"}, {"source": "src_orifice_plate_orificeparams", "target": "src_orifice_plate_orificeparams_save_interval", "relation": "defines", "confidence": "EXTRACTED", "source_file": "src/orifice_plate.cpp", "source_location": "L41", "weight": 1.0, "context": "field"}, {"source": "src_orifice_plate_orificeparams", "target": "src_orifice_plate_orificeparams_length_scale", "relation": "defines", "confidence": "EXTRACTED", "source_file": "src/orifice_plate.cpp", "source_location": "L42", "weight": 1.0, "context": "field"}, {"source": "src_orifice_plate_orificeparams", "target": "string", "relation": "references", "confidence": "EXTRACTED", "source_file": "src/orifice_plate.cpp", "source_location": "L43", "weight": 1.0, "context": "field"}, {"source": "src_orifice_plate_orificeparams", "target": "src_orifice_plate_orificeparams_config", "relation": "defines", "confidence": "EXTRACTED", "source_file": "src/orifice_plate.cpp", "source_location": "L43", "weight": 1.0, "context": "field"}, {"source": "src_orifice_plate_orificeparams", "target": "src_orifice_plate_orificeparams_hole_width", "relation": "defines", "confidence": "EXTRACTED", "source_file": "src/orifice_plate.cpp", "source_location": "L44", "weight": 1.0, "context": "field"}, {"source": "src_orifice_plate_orificeparams", "target": "src_orifice_plate_orificeparams_plate_thickness", "relation": "defines", "confidence": "EXTRACTED", "source_file": "src/orifice_plate.cpp", "source_location": "L45", "weight": 1.0, "context": "field"}, {"source": "src_orifice_plate_orificeparams", "target": "vector", "relation": "references", "confidence": "EXTRACTED", "source_file": "src/orifice_plate.cpp", "source_location": "L46", "weight": 1.0, "context": "field"}, {"source": "src_orifice_plate_orificeparams", "target": "src_orifice_plate_orificeparams_plate_cx", "relation": "defines", "confidence": "EXTRACTED", "source_file": "src/orifice_plate.cpp", "source_location": "L46", "weight": 1.0, "context": "field"}, {"source": "src_orifice_plate_orificeparams", "target": "vector", "relation": "references", "confidence": "EXTRACTED", "source_file": "src/orifice_plate.cpp", "source_location": "L47", "weight": 1.0, "context": "field"}, {"source": "src_orifice_plate_orificeparams", "target": "vector", "relation": "references", "confidence": "EXTRACTED", "source_file": "src/orifice_plate.cpp", "source_location": "L47", "weight": 1.0, "context": "generic_arg"}, {"source": "src_orifice_plate_orificeparams", "target": "src_orifice_plate_orificeparams_holes_cy", "relation": "defines", "confidence": "EXTRACTED", "source_file": "src/orifice_plate.cpp", "source_location": "L47", "weight": 1.0, "context": "field"}, {"source": "users_ajeet_projects_lbm_2d_src_orifice_plate_cpp", "target": "src_orifice_plate_compute_params", "relation": "contains", "confidence": "EXTRACTED", "source_file": "src/orifice_plate.cpp", "source_location": "L50", "weight": 1.0}, {"source": "src_orifice_plate_compute_params", "target": "src_orifice_plate_orificeparams", "relation": "references", "confidence": "EXTRACTED", "source_file": "src/orifice_plate.cpp", "source_location": "L50", "weight": 1.0, "context": "return_type"}, {"source": "src_orifice_plate_compute_params", "target": "string", "relation": "references", "confidence": "EXTRACTED", "source_file": "src/orifice_plate.cpp", "source_location": "L50", "weight": 1.0, "context": "parameter_type"}, {"source": "users_ajeet_projects_lbm_2d_src_orifice_plate_cpp", "target": "src_orifice_plate_place_orifice_plates", "relation": "contains", "confidence": "EXTRACTED", "source_file": "src/orifice_plate.cpp", "source_location": "L95", "weight": 1.0}, {"source": "src_orifice_plate_place_orifice_plates", "target": "lbmcapabilities", "relation": "references", "confidence": "EXTRACTED", "source_file": "src/orifice_plate.cpp", "source_location": "L95", "weight": 1.0, "context": "parameter_type"}, {"source": "src_orifice_plate_place_orifice_plates", "target": "src_orifice_plate_orificeparams", "relation": "references", "confidence": "EXTRACTED", "source_file": "src/orifice_plate.cpp", "source_location": "L95", "weight": 1.0, "context": "parameter_type"}, {"source": "users_ajeet_projects_lbm_2d_src_orifice_plate_cpp", "target": "src_orifice_plate_main", "relation": "contains", "confidence": "EXTRACTED", "source_file": "src/orifice_plate.cpp", "source_location": "L117", "weight": 1.0}, {"source": "src_orifice_plate_main", "target": "src_orifice_plate_compute_params", "relation": "calls", "context": "call", "confidence": "EXTRACTED", "source_file": "src/orifice_plate.cpp", "source_location": "L154", "weight": 1.0}, {"source": "src_orifice_plate_main", "target": "src_orifice_plate_place_orifice_plates", "relation": "calls", "context": "call", "confidence": "EXTRACTED", "source_file": "src/orifice_plate.cpp", "source_location": "L157", "weight": 1.0}], "raw_calls": [{"caller_nid": "src_orifice_plate_compute_params", "callee": "push_back", "is_member_call": true, "source_file": "/Users/ajeet/Projects/lbm-2d/src/orifice_plate.cpp", "source_location": "L67"}, {"caller_nid": "src_orifice_plate_compute_params", "callee": "push_back", "is_member_call": true, "source_file": "/Users/ajeet/Projects/lbm-2d/src/orifice_plate.cpp", "source_location": "L68"}, {"caller_nid": "src_orifice_plate_compute_params", "callee": "push_back", "is_member_call": true, "source_file": "/Users/ajeet/Projects/lbm-2d/src/orifice_plate.cpp", "source_location": "L70"}, {"caller_nid": "src_orifice_plate_compute_params", "callee": "push_back", "is_member_call": true, "source_file": "/Users/ajeet/Projects/lbm-2d/src/orifice_plate.cpp", "source_location": "L71"}, {"caller_nid": "src_orifice_plate_compute_params", "callee": "push_back", "is_member_call": true, "source_file": "/Users/ajeet/Projects/lbm-2d/src/orifice_plate.cpp", "source_location": "L76"}, {"caller_nid": "src_orifice_plate_compute_params", "callee": "push_back", "is_member_call": true, "source_file": "/Users/ajeet/Projects/lbm-2d/src/orifice_plate.cpp", "source_location": "L77"}, {"caller_nid": "src_orifice_plate_compute_params", "callee": "push_back", "is_member_call": true, "source_file": "/Users/ajeet/Projects/lbm-2d/src/orifice_plate.cpp", "source_location": "L83"}, {"caller_nid": "src_orifice_plate_compute_params", "callee": "push_back", "is_member_call": true, "source_file": "/Users/ajeet/Projects/lbm-2d/src/orifice_plate.cpp", "source_location": "L84"}, {"caller_nid": "src_orifice_plate_place_orifice_plates", "callee": "size", "is_member_call": true, "source_file": "/Users/ajeet/Projects/lbm-2d/src/orifice_plate.cpp", "source_location": "L96"}, {"caller_nid": "src_orifice_plate_place_orifice_plates", "callee": "node_index", "is_member_call": false, "source_file": "/Users/ajeet/Projects/lbm-2d/src/orifice_plate.cpp", "source_location": "L111"}, {"caller_nid": "src_orifice_plate_main", "callee": "stod", "is_member_call": true, "source_file": "/Users/ajeet/Projects/lbm-2d/src/orifice_plate.cpp", "source_location": "L132"}, {"caller_nid": "src_orifice_plate_main", "callee": "stoi", "is_member_call": true, "source_file": "/Users/ajeet/Projects/lbm-2d/src/orifice_plate.cpp", "source_location": "L133"}, {"caller_nid": "src_orifice_plate_main", "callee": "find", "is_member_call": true, "source_file": "/Users/ajeet/Projects/lbm-2d/src/orifice_plate.cpp", "source_location": "L134"}, {"caller_nid": "src_orifice_plate_main", "callee": "stod", "is_member_call": true, "source_file": "/Users/ajeet/Projects/lbm-2d/src/orifice_plate.cpp", "source_location": "L135"}, {"caller_nid": "src_orifice_plate_main", "callee": "stoi", "is_member_call": true, "source_file": "/Users/ajeet/Projects/lbm-2d/src/orifice_plate.cpp", "source_location": "L137"}, {"caller_nid": "src_orifice_plate_main", "callee": "compute_equilibrium", "is_member_call": false, "source_file": "/Users/ajeet/Projects/lbm-2d/src/orifice_plate.cpp", "source_location": "L162"}, {"caller_nid": "src_orifice_plate_main", "callee": "to_string", "is_member_call": true, "source_file": "/Users/ajeet/Projects/lbm-2d/src/orifice_plate.cpp", "source_location": "L167"}, {"caller_nid": "src_orifice_plate_main", "callee": "filesystem::create_directories", "is_member_call": true, "source_file": "/Users/ajeet/Projects/lbm-2d/src/orifice_plate.cpp", "source_location": "L169"}, {"caller_nid": "src_orifice_plate_main", "callee": "save_meta_json", "is_member_call": false, "source_file": "/Users/ajeet/Projects/lbm-2d/src/orifice_plate.cpp", "source_location": "L171"}, {"caller_nid": "src_orifice_plate_main", "callee": "to_string", "is_member_call": true, "source_file": "/Users/ajeet/Projects/lbm-2d/src/orifice_plate.cpp", "source_location": "L179"}, {"caller_nid": "src_orifice_plate_main", "callee": "size", "is_member_call": true, "source_file": "/Users/ajeet/Projects/lbm-2d/src/orifice_plate.cpp", "source_location": "L182"}, {"caller_nid": "src_orifice_plate_main", "callee": "execute_time_step", "is_member_call": false, "source_file": "/Users/ajeet/Projects/lbm-2d/src/orifice_plate.cpp", "source_location": "L190"}, {"caller_nid": "src_orifice_plate_main", "callee": "save_forces_jsonl", "is_member_call": false, "source_file": "/Users/ajeet/Projects/lbm-2d/src/orifice_plate.cpp", "source_location": "L198"}, {"caller_nid": "src_orifice_plate_main", "callee": "save_json_frame", "is_member_call": false, "source_file": "/Users/ajeet/Projects/lbm-2d/src/orifice_plate.cpp", "source_location": "L201"}, {"caller_nid": "src_orifice_plate_main", "callee": "setw", "is_member_call": true, "source_file": "/Users/ajeet/Projects/lbm-2d/src/orifice_plate.cpp", "source_location": "L205"}, {"caller_nid": "src_orifice_plate_main", "callee": "setprecision", "is_member_call": true, "source_file": "/Users/ajeet/Projects/lbm-2d/src/orifice_plate.cpp", "source_location": "L206"}, {"caller_nid": "src_orifice_plate_main", "callee": "setprecision", "is_member_call": true, "source_file": "/Users/ajeet/Projects/lbm-2d/src/orifice_plate.cpp", "source_location": "L207"}]}